Workbook
Name Slicer_Category: #N/A
Name Slicer_Months__Date: #N/A
Name Slicer_Region: #N/A

Sheet Project Instructions
A1: PR. Final Project - "Data Intelligence Dashboard"
A2: Dataset: Use the 'Final Project Dataset' sheet containing 200+ records of customer transactions. Objective: Create a full-fledged analysis and reporting solution using Excel to analyze customer transactions, find insights, and build visualizations and dashboards. Key Topics to Implement: - Date & Time Functions: TODAY, NOW, DATEDIF, EOMONTH - FILTER Function for multi-value returns - Conditional Formatting with Icons/Arrows - Create Timestamp (using NOW and iterative calculations) - WHAT-IF Analysis: Scenario Manager, Goal Seek - Linear Regression using Data Analysis Toolpak - Data Analysis & Storytelling from the dataset - Use GroupBy concepts to find High-Value Customers using formulas - Create Dashboard using: - Pivot Tables - Pivot Charts (Bar, Line, Pie) - Slicers and Timelines - KPI Indicators with Conditional Formatting - Find most frequently purchased product or repeating names using formulas - Compare two lists and extract matching names in a new column - Create Abbreviations using TEXT functions - Build a final report with insights and storytelling Deliverable: - Well-structured workbook with multiple sheets (Raw Data, Analysis, Visualizations, Dashboard) - Summary Insights with key metrics: Total Revenue, Top Customers, Most Sold Products, Regional Sales - Use of all required formulas and functions as listed above

Sheet Dashboard

Sheet Pie 
A3: Row Labels | B3: Sum of Total_Amount
A4: Appliances | B4: 8338.74
A5: Electronics | B5: 171756.05
A6: Furniture | B6: 49097.68
A7: (blank)
A8: Grand Total | B8: 229192.47
B10: =GETPIVOTDATA("Total_Amount",$A$3) -> 229192.47

Sheet Total
A1: Row Labels | B1: Count of Customer_ID
A2: Appliances | B2: 43
A3: Electronics | B3: 131
A4: Furniture | B4: 76
A5: (blank)
A6: Grand Total | B6: 250
B7: =GETPIVOTDATA("Customer_ID",$A$1) -> 250
A9: Row Labels | B9: Sum of Quantity
A10: Appliances | B10: 126
A11: Electronics | B11: 395
A12: Furniture | B12: 232
A13: (blank)
A14: Grand Total | B14: 753
B15: =GETPIVOTDATA("Quantity",$A$9) -> 753

Sheet Regression
A1: Linear Regression using Data Analysis Toolpak
A3: SUMMARY OUTPUT
A5: Regression Statistics
A6: Multiple R | B6: 0.45808036
A7: R Square | B7: 0.20983762
A8: Adjusted R Square | B8: 0.20665148
A9: Standard Error | B9: 919.60715
A10: Observations | B10: 250
A12: ANOVA
B13: df | C13: SS | D13: MS | E13: F | F13: Significance F
A14: Regression | B14: 1 | C14: 55695917 | D14: 55695917 | E14: 65.859537 | F14: 2.2586479e-14
A15: Residual | B15: 248 | C15: 2.0972797e+08 | D15: 845677.32
A16: Total | B16: 249 | C16: 2.6542389e+08
B18: Coefficients | C18: Standard Error | D18: t Stat | E18: P-value | F18: Lower 95% | G18: Upper 95% | H18: Lower 95.0% | I18: Upper 95.0%
A19: Intercept | B19: -148.85465 | C19: 143.61334 | D19: -1.0364959 | E19: 0.3009804 | F19: -431.712 | G19: 134.0027 | H19: -431.712 | I19: 134.0027
A20: Quantity | B20: 353.793 | C20: 43.595323 | D20: 8.1153889 | E20: 2.2586479e-14 | F20: 267.92872 | G20: 439.65729 | H20: 267.92872 | I20: 439.65729

Sheet Scenario Summary
B2: Scenario Summary
D3: Current Values: | E3: Best Case | F3: Average Case | G3: Worst Case
E4: Created by Nitesh kumar on 27-03-2026 | F4: Created by Nitesh kumar on 27-03-2026 Modified by Nitesh kumar on 27-03-2026 | G4: Created by Nitesh kumar on 27-03-2026 Modified by Nitesh kumar on 27-03-2026
B5: Changing Cells:
C6: $R$63 | D6: 3 | E6: 5 | F6: 3 | G6: 1
C7: $R$62 | D7: 2000 | E7: 699.99 | F7: 699.99 | G7: 699.99
B8: Result Cells:
C9: $R$64 | D9: 6000 | E9: 3499.95 | F9: 2099.97 | G9: 699.99
B10: Notes: Current Values column represents values of changing cells at
B11: time Scenario Summary Report was created. Changing cells for each
B12: scenario are highlighted in gray.

Sheet Bar_chart
A3: Row Labels | B3: Sum of Total_Amount
A4: Blender | B4: 5219.13
A5: Bookshelf | B5: 15298.98
A6: Coffee Maker | B6: 3119.61
A7: Desk | B7: 23399.22
A8: Headphones | B8: 7049.53
A9: Keyboard | B9: 8009.11
A10: Laptop | B10: 67499.25
A11: Monitor | B11: 21999.12
A12: Office Chair | B12: 10399.48
A13: Smartphone | B13: 67199.04
A14: Grand Total | B14: 229192.47

Sheet Doughnut
A3: Row Labels | B3: Sum of Total_Amount
A4: Central | B4: 41288.34
A5: East | B5: 59288.39
A6: North | B6: 50808.31
A7: South | B7: 36398.75
A8: West | B8: 41408.68
A9: (blank)
A10: Grand Total | B10: 229192.47

Sheet Line_chart
A3: Row Labels | B3: Sum of Total_Amount
A4: <11-04-2024
A5: Jan | B5: 25799.15
A6: Feb | B6: 16069.38
A7: Mar | B7: 19899.38
A8: Apr | B8: 27899.16
A9: May | B9: 17039.35
A10: Jun | B10: 19299.45
A11: Jul | B11: 18479.4
A12: Aug | B12: 15759.43
A13: Sep | B13: 12989.51
A14: Oct | B14: 20609.52
A15: Nov | B15: 12309.44
A16: Dec | B16: 23039.3
A17: Grand Total | B17: 229192.47
B24: =B17 -> 229192.47

Sheet Bar_chart1
A3: Row Labels | B3: Sum of Quantity
A4: Blender | B4: 87
A5: Bookshelf | B5: 102
A6: Coffee Maker | B6: 39
A7: Desk | B7: 78
A8: Headphones | B8: 47
A9: Keyboard | B9: 89
A10: Laptop | B10: 75
A11: Monitor | B11: 88
A12: Office Chair | B12: 52
A13: Smartphone | B13: 96
A14: Grand Total | B14: 753
B16: =GETPIVOTDATA("Quantity",$A$3) -> 753

Sheet Bar_Chart2
A3: Row Labels | B3: Sum of Total_Amount
A4: Mark Carter | B4: 15659.65
A5: Edward Mitchell | B5: 11919.77
A6: Barbara Young | B6: 10649.8
A7: Patricia Moore | B7: 9799.73
A8: Paul Baker | B8: 8309.74
A9: Grand Total | B9: 56338.69

Sheet Sheet1

Sheet Final Project Dataset
A1: Transaction_ID | B1: Date | C1: Customer_ID | D1: Customer_Name | E1: Product_ID | F1: Product_Name | G1: Category | H1: Quantity | I1: Unit_Price | J1: Payment_Method | K1: Region | L1: Customer_Segment | M1: Customer_Since | N1: Total_Amount | O1: timestamp | P1: Most_Frequently_Purchase_Product | Q1: Abbreviations
A2: TRX0155 | B2: 45393 | C2: CUST023 | D2: Paul Baker | E2: P009 | F2: Monitor | G2: Electronics | H2: 3 | I2: 249.99 | J2: Cash | K2: Central | L2: Basic | M2: 44425 | N2: 749.97 | O2: =IF(A2<>"", IF(O2="", NOW(), O2), "") -> 0 | P2: =COUNTIF($F:$F,F2) -> 26 | Q2: =LEFT(D2,1) & MID(D2,FIND(" ",D2)+1,1) -> PB | V2: Date & Time Functions: TODAY, NOW, DATEDIF, EOMONTH
A3: TRX0023 | B3: 45396 | C3: CUST013 | D3: Joseph Jackson | E3: P009 | F3: Monitor | G3: Electronics | H3: 3 | I3: 249.99 | J3: Credit Card | K3: Central | L3: Premium | M3: 44575 | N3: 749.97 | O3: =IF(A3<>"", IF(O3="", NOW(), O3), "") -> 0 | P3: =COUNTIF($F:$F,F3) -> 26 | Q3: =LEFT(D3,1) & MID(D3,FIND(" ",D3)+1,1) -> JJ | S3: Total_Customer | T3: =COUNTA(_xlfn.UNIQUE(D2:D251)) -> 50 | V3: 1. Display current date (TODAY)
A4: TRX0139 | B4: 45399 | C4: CUST021 | D4: Kevin Scott | E4: P005 | F4: Blender | G4: Appliances | H4: 3 | I4: 59.99 | J4: PayPal | K4: South | L4: Standard | M4: 45262 | N4: 179.97 | O4: =IF(A4<>"", IF(O4="", NOW(), O4), "") -> 0 | P4: =COUNTIF($F:$F,F4) -> 29 | Q4: =LEFT(D4,1) & MID(D4,FIND(" ",D4)+1,1) -> KS | V4: =TODAY() -> 46109
A5: TRX0043 | B5: 45400 | C5: CUST046 | D5: Kathleen Bennett | E5: P005 | F5: Blender | G5: Appliances | H5: 3 | I5: 59.99 | J5: Cash | K5: North | L5: Premium | M5: 45114 | N5: 179.97 | O5: =IF(A5<>"", IF(O5="", NOW(), O5), "") -> 0 | P5: =COUNTIF($F:$F,F5) -> 29 | Q5: =LEFT(D5,1) & MID(D5,FIND(" ",D5)+1,1) -> KB
A6: TRX0212 | B6: 45400 | C6: CUST003 | D6: Michael Brown | E6: P008 | F6: Bookshelf | G6: Furniture | H6: 5 | I6: 149.99 | J6: Credit Card | K6: North | L6: Premium | M6: 45295 | N6: 749.95 | O6: =IF(A6<>"", IF(O6="", NOW(), O6), "") -> 0 | P6: =COUNTIF($F:$F,F6) -> 35 | Q6: =LEFT(D6,1) & MID(D6,FIND(" ",D6)+1,1) -> MB | V6: 2. Display current date and time
A7: TRX0092 | B7: 45403 | C7: CUST024 | D7: Dorothy Nelson | E7: P005 | F7: Blender | G7: Appliances | H7: 2 | I7: 59.99 | J7: Cash | K7: West | L7: Standard | M7: 44746 | N7: 119.98 | O7: =IF(A7<>"", IF(O7="", NOW(), O7), "") -> 0 | P7: =COUNTIF($F:$F,F7) -> 29 | Q7: =LEFT(D7,1) & MID(D7,FIND(" ",D7)+1,1) -> DN | V7: =NOW() -> 46109.519
A8: TRX0193 | B8: 45403 | C8: CUST024 | D8: Dorothy Nelson | E8: P003 | F8: Headphones | G8: Electronics | H8: 5 | I8: 149.99 | J8: Credit Card | K8: Central | L8: Standard | M8: 44418 | N8: 749.95 | O8: =IF(A8<>"", IF(O8="", NOW(), O8), "") -> 0 | P8: =COUNTIF($F:$F,F8) -> 16 | Q8: =LEFT(D8,1) & MID(D8,FIND(" ",D8)+1,1) -> DN | T8: =T3 -> 50
A9: TRX0240 | B9: 45403 | C9: CUST017 | D9: Charles Allen | E9: P005 | F9: Blender | G9: Appliances | H9: 3 | I9: 59.99 | J9: Debit Card | K9: South | L9: Basic | M9: 45007 | N9: 179.97 | O9: =IF(A9<>"", IF(O9="", NOW(), O9), "") -> 0 | P9: =COUNTIF($F:$F,F9) -> 29 | Q9: =LEFT(D9,1) & MID(D9,FIND(" ",D9)+1,1) -> CA | V9: 3.Calculate customer tenure (years)
A10: TRX0135 | B10: 45405 | C10: CUST009 | D10: Robert Thomas | E10: P001 | F10: Laptop | G10: Electronics | H10: 3 | I10: 899.99 | J10: PayPal | K10: East | L10: Standard | M10: 45299 | N10: 2699.97 | O10: =IF(A10<>"", IF(O10="", NOW(), O10), "") -> 0 | P10: =COUNTIF($F:$F,F10) -> 24 | Q10: =LEFT(D10,1) & MID(D10,FIND(" ",D10)+1,1) -> RT | V10: Customer ID | W10: Customer_Since | X10: Customer_Tenure
A11: TRX0185 | B11: 45408 | C11: CUST026 | D11: Karen Hill | E11: P005 | F11: Blender | G11: Appliances | H11: 3 | I11: 59.99 | J11: Cash | K11: West | L11: Premium | M11: 45207 | N11: 179.97 | O11: =IF(A11<>"", IF(O11="", NOW(), O11), "") -> 0 | P11: =COUNTIF($F:$F,F11) -> 29 | Q11: =LEFT(D11,1) & MID(D11,FIND(" ",D11)+1,1) -> KH | S11: Total Orders | T11: =COUNTA(_xlfn.UNIQUE(A:A)) -> 252 | V11: CUST023 | W11: 44425 | X11: =DATEDIF(W11,TODAY(),"Y") -> 4
A12: TRX0138 | B12: 45408 | C12: CUST022 | D12: Susan Green | E12: P008 | F12: Bookshelf | G12: Furniture | H12: 1 | I12: 149.99 | J12: Credit Card | K12: West | L12: Standard | M12: 45103 | N12: 149.99 | O12: =IF(A12<>"", IF(O12="", NOW(), O12), "") -> 0 | P12: =COUNTIF($F:$F,F12) -> 35 | Q12: =LEFT(D12,1) & MID(D12,FIND(" ",D12)+1,1) -> SG
A13: TRX0209 | B13: 45408 | C13: CUST046 | D13: Kathleen Bennett | E13: P008 | F13: Bookshelf | G13: Furniture | H13: 5 | I13: 149.99 | J13: Debit Card | K13: North | L13: Basic | M13: 44830 | N13: 749.95 | O13: =IF(A13<>"", IF(O13="", NOW(), O13), "") -> 0 | P13: =COUNTIF($F:$F,F13) -> 35 | Q13: =LEFT(D13,1) & MID(D13,FIND(" ",D13)+1,1) -> KB | V13: 4. Get last day of the month
A14: TRX0246 | B14: 45408 | C14: CUST041 | D14: Peter Richardson | E14: P008 | F14: Bookshelf | G14: Furniture | H14: 3 | I14: 149.99 | J14: Cash | K14: North | L14: Premium | M14: 44806 | N14: 449.97 | O14: =IF(A14<>"", IF(O14="", NOW(), O14), "") -> 0 | P14: =COUNTIF($F:$F,F14) -> 35 | Q14: =LEFT(D14,1) & MID(D14,FIND(" ",D14)+1,1) -> PR | T14: =T11 -> 252 | V14: DATE | W14: LAST_DAY
A15: TRX0067 | B15: 45409 | C15: CUST043 | D15: Dennis Gray | E15: P005 | F15: Blender | G15: Appliances | H15: 3 | I15: 59.99 | J15: Credit Card | K15: North | L15: Standard | M15: 45351 | N15: 179.97 | O15: =IF(A15<>"", IF(O15="", NOW(), O15), "") -> 0 | P15: =COUNTIF($F:$F,F15) -> 29 | Q15: =LEFT(D15,1) & MID(D15,FIND(" ",D15)+1,1) -> DG | V15: =TODAY() -> 46109 | W15: =EOMONTH(V15,0) -> 46112
A16: TRX0191 | B16: 45409 | C16: CUST038 | D16: Michelle Rogers | E16: P002 | F16: Smartphone | G16: Electronics | H16: 3 | I16: 699.99 | J16: Credit Card | K16: West | L16: Basic | M16: 44577 | N16: 2099.97 | O16: =IF(A16<>"", IF(O16="", NOW(), O16), "") -> 0 | P16: =COUNTIF($F:$F,F16) -> 31 | Q16: =LEFT(D16,1) & MID(D16,FIND(" ",D16)+1,1) -> MR
A17: TRX0230 | B17: 45409 | C17: CUST027 | D17: George Adams | E17: P001 | F17: Laptop | G17: Electronics | H17: 1 | I17: 899.99 | J17: Debit Card | K17: North | L17: Standard | M17: 44920 | N17: 899.99 | O17: =IF(A17<>"", IF(O17="", NOW(), O17), "") -> 0 | P17: =COUNTIF($F:$F,F17) -> 24 | Q17: =LEFT(D17,1) & MID(D17,FIND(" ",D17)+1,1) -> GA
A18: TRX0049 | B18: 45410 | C18: CUST025 | D18: Mark Carter | E18: P008 | F18: Bookshelf | G18: Furniture | H18: 4 | I18: 149.99 | J18: Debit Card | K18: North | L18: Premium | M18: 45374 | N18: 599.96 | O18: =IF(A18<>"", IF(O18="", NOW(), O18), "") -> 0 | P18: =COUNTIF($F:$F,F18) -> 35 | Q18: =LEFT(D18,1) & MID(D18,FIND(" ",D18)+1,1) -> MC | V18: Filter transactions where Category is Electronics and Payment Method is Credit Card
A19: TRX0134 | B19: 45410 | C19: CUST010 | D19: Maria Garcia | E19: P002 | F19: Smartphone | G19: Electronics | H19: 2 | I19: 699.99 | J19: Cash | K19: North | L19: Basic | M19: 44781 | N19: 1399.98 | O19: =IF(A19<>"", IF(O19="", NOW(), O19), "") -> 0 | P19: =COUNTIF($F:$F,F19) -> 31 | Q19: =LEFT(D19,1) & MID(D19,FIND(" ",D19)+1,1) -> MG | V19: {=_xlfn._xlws.FILTER(A2:N251,(G2:G251="Electronics")*(J2:J251="Credit Card"))} -> TRX0023 | W19: 45396 | X19: CUST013 | Y19: Joseph Jackson | Z19: P009 | AA19: Monitor | AB19: Electronics | AC19: 3 | AD19: 249.99 | AE19: Credit Card | AF19: Central | AG19: Premium | AH19: 44575 | AI19: 749.97
A20: TRX0122 | B20: 45410 | C20: CUST025 | D20: Mark Carter | E20: P001 | F20: Laptop | G20: Electronics | H20: 4 | I20: 899.99 | J20: Credit Card | K20: West | L20: Standard | M20: 45327 | N20: 3599.96 | O20: =IF(A20<>"", IF(O20="", NOW(), O20), "") -> 0 | P20: =COUNTIF($F:$F,F20) -> 24 | Q20: =LEFT(D20,1) & MID(D20,FIND(" ",D20)+1,1) -> MC | V20: TRX0193 | W20: 45403 | X20: CUST024 | Y20: Dorothy Nelson | Z20: P003 | AA20: Headphones | AB20: Electronics | AC20: 5 | AD20: 149.99 | AE20: Credit Card | AF20: Central | AG20: Standard | AH20: 44418 | AI20: 749.95
A21: TRX0222 | B21: 45410 | C21: CUST048 | D21: Virginia Sanders | E21: P009 | F21: Monitor | G21: Electronics | H21: 3 | I21: 249.99 | J21: Credit Card | K21: North | L21: Premium | M21: 45224 | N21: 749.97 | O21: =IF(A21<>"", IF(O21="", NOW(), O21), "") -> 0 | P21: =COUNTIF($F:$F,F21) -> 26 | Q21: =LEFT(D21,1) & MID(D21,FIND(" ",D21)+1,1) -> VS | V21: TRX0191 | W21: 45409 | X21: CUST038 | Y21: Michelle Rogers | Z21: P002 | AA21: Smartphone | AB21: Electronics | AC21: 3 | AD21: 699.99 | AE21: Credit Card | AF21: West | AG21: Basic | AH21: 44577 | AI21: 2099.97
A22: TRX0231 | B22: 45412 | C22: CUST018 | D22: Barbara Young | E22: P002 | F22: Smartphone | G22: Electronics | H22: 5 | I22: 699.99 | J22: Cash | K22: West | L22: Basic | M22: 45167 | N22: 3499.95 | O22: =IF(A22<>"", IF(O22="", NOW(), O22), "") -> 0 | P22: =COUNTIF($F:$F,F22) -> 31 | Q22: =LEFT(D22,1) & MID(D22,FIND(" ",D22)+1,1) -> BY | V22: TRX0122 | W22: 45410 | X22: CUST025 | Y22: Mark Carter | Z22: P001 | AA22: Laptop | AB22: Electronics | AC22: 4 | AD22: 899.99 | AE22: Credit Card | AF22: West | AG22: Standard | AH22: 45327 | AI22: 3599.96
A23: TRX0239 | B23: 45413 | C23: CUST012 | D23: Patricia Moore | E23: P002 | F23: Smartphone | G23: Electronics | H23: 4 | I23: 699.99 | J23: Cash | K23: East | L23: Standard | M23: 44409 | N23: 2799.96 | O23: =IF(A23<>"", IF(O23="", NOW(), O23), "") -> 0 | P23: =COUNTIF($F:$F,F23) -> 31 | Q23: =LEFT(D23,1) & MID(D23,FIND(" ",D23)+1,1) -> PM | V23: TRX0222 | W23: 45410 | X23: CUST048 | Y23: Virginia Sanders | Z23: P009 | AA23: Monitor | AB23: Electronics | AC23: 3 | AD23: 249.99 | AE23: Credit Card | AF23: North | AG23: Premium | AH23: 45224 | AI23: 749.97
A24: TRX0204 | B24: 45415 | C24: CUST044 | D24: Cynthia Price | E24: P009 | F24: Monitor | G24: Electronics | H24: 4 | I24: 249.99 | J24: PayPal | K24: North | L24: Standard | M24: 44468 | N24: 999.96 | O24: =IF(A24<>"", IF(O24="", NOW(), O24), "") -> 0 | P24: =COUNTIF($F:$F,F24) -> 26 | Q24: =LEFT(D24,1) & MID(D24,FIND(" ",D24)+1,1) -> CP | V24: TRX0071 | W24: 45422 | X24: CUST036 | Y24: Nancy Collins | Z24: P009 | AA24: Monitor | AB24: Electronics | AC24: 5 | AD24: 249.99 | AE24: Credit Card | AF24: West | AG24: Standard | AH24: 44525 | AI24: 1249.95
A25: TRX0242 | B25: 45416 | C25: CUST025 | D25: Mark Carter | E25: P007 | F25: Desk | G25: Furniture | H25: 4 | I25: 299.99 | J25: Cash | K25: West | L25: Premium | M25: 44716 | N25: 1199.96 | O25: =IF(A25<>"", IF(O25="", NOW(), O25), "") -> 0 | P25: =COUNTIF($F:$F,F25) -> 26 | Q25: =LEFT(D25,1) & MID(D25,FIND(" ",D25)+1,1) -> MC | V25: TRX0041 | W25: 45432 | X25: CUST021 | Y25: Kevin Scott | Z25: P001 | AA25: Laptop | AB25: Electronics | AC25: 1 | AD25: 899.99 | AE25: Credit Card | AF25: West | AG25: Premium | AH25: 44578 | AI25: 899.99
A26: TRX0071 | B26: 45422 | C26: CUST036 | D26: Nancy Collins | E26: P009 | F26: Monitor | G26: Electronics | H26: 5 | I26: 249.99 | J26: Credit Card | K26: West | L26: Standard | M26: 44525 | N26: 1249.95 | O26: =IF(A26<>"", IF(O26="", NOW(), O26), "") -> 0 | P26: =COUNTIF($F:$F,F26) -> 26 | Q26: =LEFT(D26,1) & MID(D26,FIND(" ",D26)+1,1) -> NC | V26: TRX0208 | W26: 45446 | X26: CUST004 | Y26: Sarah Davis | Z26: P010 | AA26: Keyboard | AB26: Electronics | AC26: 5 | AD26: 89.99 | AE26: Credit Card | AF26: East | AG26: Standard | AH26: 44587 | AI26: 449.95
A27: TRX0040 | B27: 45424 | C27: CUST022 | D27: Susan Green | E27: P007 | F27: Desk | G27: Furniture | H27: 5 | I27: 299.99 | J27: PayPal | K27: East | L27: Basic | M27: 45168 | N27: 1499.95 | O27: =IF(A27<>"", IF(O27="", NOW(), O27), "") -> 0 | P27: =COUNTIF($F:$F,F27) -> 26 | Q27: =LEFT(D27,1) & MID(D27,FIND(" ",D27)+1,1) -> SG | V27: TRX0234 | W27: 45449 | X27: CUST013 | Y27: Joseph Jackson | Z27: P009 | AA27: Monitor | AB27: Electronics | AC27: 5 | AD27: 249.99 | AE27: Credit Card | AF27: East | AG27: Standard | AH27: 44707 | AI27: 1249.95
A28: TRX0235 | B28: 45424 | C28: CUST014 | D28: Linda Martin | E28: P004 | F28: Coffee Maker | G28: Appliances | H28: 3 | I28: 79.99 | J28: PayPal | K28: East | L28: Premium | M28: 45012 | N28: 239.97 | O28: =IF(A28<>"", IF(O28="", NOW(), O28), "") -> 0 | P28: =COUNTIF($F:$F,F28) -> 14 | Q28: =LEFT(D28,1) & MID(D28,FIND(" ",D28)+1,1) -> LM | V28: TRX0121 | W28: 45449 | X28: CUST028 | Y28: Betty Campbell | Z28: P010 | AA28: Keyboard | AB28: Electronics | AC28: 1 | AD28: 89.99 | AE28: Credit Card | AF28: South | AG28: Standard | AH28: 44582 | AI28: 89.99
A29: TRX0004 | B29: 45424 | C29: CUST012 | D29: Patricia Moore | E29: P010 | F29: Keyboard | G29: Electronics | H29: 5 | I29: 89.99 | J29: Cash | K29: North | L29: Premium | M29: 44919 | N29: 449.95 | O29: =IF(A29<>"", IF(O29="", NOW(), O29), "") -> 0 | P29: =COUNTIF($F:$F,F29) -> 34 | Q29: =LEFT(D29,1) & MID(D29,FIND(" ",D29)+1,1) -> PM | V29: TRX0115 | W29: 45459 | X29: CUST012 | Y29: Patricia Moore | Z29: P010 | AA29: Keyboard | AB29: Electronics | AC29: 2 | AD29: 89.99 | AE29: Credit Card | AF29: South | AG29: Premium | AH29: 44471 | AI29: 179.98
A30: TRX0063 | B30: 45425 | C30: CUST030 | D30: Helen Roberts | E30: P005 | F30: Blender | G30: Appliances | H30: 2 | I30: 59.99 | J30: Debit Card | K30: Central | L30: Standard | M30: 45214 | N30: 119.98 | O30: =IF(A30<>"", IF(O30="", NOW(), O30), "") -> 0 | P30: =COUNTIF($F:$F,F30) -> 29 | Q30: =LEFT(D30,1) & MID(D30,FIND(" ",D30)+1,1) -> HR | V30: TRX0154 | W30: 45459 | X30: CUST023 | Y30: Paul Baker | Z30: P001 | AA30: Laptop | AB30: Electronics | AC30: 5 | AD30: 899.99 | AE30: Credit Card | AF30: South | AG30: Standard | AH30: 44974 | AI30: 4499.95
A31: TRX0241 | B31: 45427 | C31: CUST029 | D31: Edward Mitchell | E31: P005 | F31: Blender | G31: Appliances | H31: 4 | I31: 59.99 | J31: Debit Card | K31: East | L31: Standard | M31: 44867 | N31: 239.96 | O31: =IF(A31<>"", IF(O31="", NOW(), O31), "") -> 0 | P31: =COUNTIF($F:$F,F31) -> 29 | Q31: =LEFT(D31,1) & MID(D31,FIND(" ",D31)+1,1) -> EM | V31: TRX0184 | W31: 45471 | X31: CUST046 | Y31: Kathleen Bennett | Z31: P002 | AA31: Smartphone | AB31: Electronics | AC31: 3 | AD31: 699.99 | AE31: Credit Card | AF31: East | AG31: Premium | AH31: 45102 | AI31: 2099.97
... A57: TRX0007 | B57: 45469 | C57: CUST009 | D57: Robert Thomas | E57: P010 | F57: Keyboard | G57: Electronics | H57: 2 | I57: 89.99 | J57: Cash | K57: West | L57: Basic | M57: 44438 | N57: 179.98 | O57: =IF(A57<>"", IF(O57="", NOW(), O57), "") -> 0 | P57: =COUNTIF($F:$F,F57) -> 34 | Q57: =LEFT(D57,1) & MID(D57,FIND(" ",D57)+1,1) -> RT | V57: TRX0233 | W57: 45723 | X57: CUST023 | Y57: Paul Baker | Z57: P010 | AA57: Keyboard | AB57: Electronics | AC57: 2 | AD57: 89.99 | AE57: Credit Card | AF57: West | AG57: Premium | AH57: 45295 | AI57: 179.98
A58: TRX0184 | B58: 45471 | C58: CUST046 | D58: Kathleen Bennett | E58: P002 | F58: Smartphone | G58: Electronics | H58: 3 | I58: 699.99 | J58: Credit Card | K58: East | L58: Premium | M58: 45102 | N58: 2099.97 | O58: =IF(A58<>"", IF(O58="", NOW(), O58), "") -> 0 | P58: =COUNTIF($F:$F,F58) -> 31 | Q58: =LEFT(D58,1) & MID(D58,FIND(" ",D58)+1,1) -> KB
A59: TRX0104 | B59: 45471 | C59: CUST012 | D59: Patricia Moore | E59: P001 | F59: Laptop | G59: Electronics | H59: 4 | I59: 899.99 | J59: Credit Card | K59: East | L59: Premium | M59: 44993 | N59: 3599.96 | O59: =IF(A59<>"", IF(O59="", NOW(), O59), "") -> 0 | P59: =COUNTIF($F:$F,F59) -> 24 | Q59: =LEFT(D59,1) & MID(D59,FIND(" ",D59)+1,1) -> PM
A60: TRX0127 | B60: 45472 | C60: CUST030 | D60: Helen Roberts | E60: P008 | F60: Bookshelf | G60: Furniture | H60: 1 | I60: 149.99 | J60: PayPal | K60: East | L60: Basic | M60: 44851 | N60: 149.99 | O60: =IF(A60<>"", IF(O60="", NOW(), O60), "") -> 0 | P60: =COUNTIF($F:$F,F60) -> 35 | Q60: =LEFT(D60,1) & MID(D60,FIND(" ",D60)+1,1) -> HR
A61: TRX0096 | B61: 45474 | C61: CUST002 | D61: Emma Wilson | E61: P010 | F61: Keyboard | G61: Electronics | H61: 2 | I61: 89.99 | J61: PayPal | K61: Central | L61: Premium | M61: 45275 | N61: 179.98 | O61: =IF(A61<>"", IF(O61="", NOW(), O61), "") -> 0 | P61: =COUNTIF($F:$F,F61) -> 34 | Q61: =LEFT(D61,1) & MID(D61,FIND(" ",D61)+1,1) -> EW | V61: WHAT-IF Analysis: Scenario Manager, Goal Seek
A62: TRX0192 | B62: 45475 | C62: CUST017 | D62: Charles Allen | E62: P010 | F62: Keyboard | G62: Electronics | H62: 1 | I62: 89.99 | J62: PayPal | K62: West | L62: Standard | M62: 44802 | N62: 89.99 | O62: =IF(A62<>"", IF(O62="", NOW(), O62), "") -> 0 | P62: =COUNTIF($F:$F,F62) -> 34 | Q62: =LEFT(D62,1) & MID(D62,FIND(" ",D62)+1,1) -> CA | V62: Unit Price | W62: 2000
A63: TRX0052 | B63: 45476 | C63: CUST022 | D63: Susan Green | E63: P010 | F63: Keyboard | G63: Electronics | H63: 1 | I63: 89.99 | J63: Cash | K63: South | L63: Standard | M63: 44611 | N63: 89.99 | O63: =IF(A63<>"", IF(O63="", NOW(), O63), "") -> 0 | P63: =COUNTIF($F:$F,F63) -> 34 | Q63: =LEFT(D63,1) & MID(D63,FIND(" ",D63)+1,1) -> SG | V63: Quntity | W63: 3
A64: TRX0070 | B64: 45476 | C64: CUST007 | D64: David Martinez | E64: P004 | F64: Coffee Maker | G64: Appliances | H64: 5 | I64: 79.99 | J64: Debit Card | K64: Central | L64: Basic | M64: 44981 | N64: 399.95 | O64: =IF(A64<>"", IF(O64="", NOW(), O64), "") -> 0 | P64: =COUNTIF($F:$F,F64) -> 14 | Q64: =LEFT(D64,1) & MID(D64,FIND(" ",D64)+1,1) -> DM | V64: Total Price | W64: =W62*W63 -> 6000
A65: TRX0086 | B65: 45481 | C65: CUST020 | D65: Margaret Wright | E65: P008 | F65: Bookshelf | G65: Furniture | H65: 1 | I65: 149.99 | J65: PayPal | K65: North | L65: Basic | M65: 44421 | N65: 149.99 | O65: =IF(A65<>"", IF(O65="", NOW(), O65), "") -> 0 | P65: =COUNTIF($F:$F,F65) -> 35 | Q65: =LEFT(D65,1) & MID(D65,FIND(" ",D65)+1,1) -> MW
A66: TRX0113 | B66: 45481 | C66: CUST003 | D66: Michael Brown | E66: P002 | F66: Smartphone | G66: Electronics | H66: 2 | I66: 699.99 | J66: PayPal | K66: East | L66: Premium | M66: 45389 | N66: 1399.98 | O66: =IF(A66<>"", IF(O66="", NOW(), O66), "") -> 0 | P66: =COUNTIF($F:$F,F66) -> 31 | Q66: =LEFT(D66,1) & MID(D66,FIND(" ",D66)+1,1) -> MB | V66: Scenario Manage
A67: TRX0114 | B67: 45481 | C67: CUST018 | D67: Barbara Young | E67: P010 | F67: Keyboard | G67: Electronics | H67: 5 | I67: 89.99 | J67: Debit Card | K67: North | L67: Premium | M67: 45161 | N67: 449.95 | O67: =IF(A67<>"", IF(O67="", NOW(), O67), "") -> 0 | P67: =COUNTIF($F:$F,F67) -> 34 | Q67: =LEFT(D67,1) & MID(D67,FIND(" ",D67)+1,1) -> BY | V67: Scenario | W67: Qty | X67: Price
A68: TRX0136 | B68: 45482 | C68: CUST049 | D68: Raymond Ross | E68: P005 | F68: Blender | G68: Appliances | H68: 4 | I68: 59.99 | J68: Cash | K68: South | L68: Standard | M68: 44509 | N68: 239.96 | O68: =IF(A68<>"", IF(O68="", NOW(), O68), "") -> 0 | P68: =COUNTIF($F:$F,F68) -> 29 | Q68: =LEFT(D68,1) & MID(D68,FIND(" ",D68)+1,1) -> RR | V68: Best | W68: 5 | X68: 699.99
A69: TRX0018 | B69: 45484 | C69: CUST013 | D69: Joseph Jackson | E69: P003 | F69: Headphones | G69: Electronics | H69: 1 | I69: 149.99 | J69: Cash | K69: Central | L69: Standard | M69: 44909 | N69: 149.99 | O69: =IF(A69<>"", IF(O69="", NOW(), O69), "") -> 0 | P69: =COUNTIF($F:$F,F69) -> 16 | Q69: =LEFT(D69,1) & MID(D69,FIND(" ",D69)+1,1) -> JJ | V69: Average | W69: 3 | X69: 699.99
A70: TRX0141 | B70: 45484 | C70: CUST033 | D70: Frank Torres | E70: P007 | F70: Desk | G70: Furniture | H70: 1 | I70: 299.99 | J70: Credit Card | K70: North | L70: Premium | M70: 44891 | N70: 299.99 | O70: =IF(A70<>"", IF(O70="", NOW(), O70), "") -> 0 | P70: =COUNTIF($F:$F,F70) -> 26 | Q70: =LEFT(D70,1) & MID(D70,FIND(" ",D70)+1,1) -> FT | V70: Worth | W70: 1 | X70: 699.99
A71: TRX0097 | B71: 45487 | C71: CUST033 | D71: Frank Torres | E71: P006 | F71: Office Chair | G71: Furniture | H71: 2 | I71: 199.99 | J71: Cash | K71: North | L71: Basic | M71: 44541 | N71: 399.98 | O71: =IF(A71<>"", IF(O71="", NOW(), O71), "") -> 0 | P71: =COUNTIF($F:$F,F71) -> 15 | Q71: =LEFT(D71,1) & MID(D71,FIND(" ",D71)+1,1) -> FT
A72: TRX0169 | B72: 45490 | C72: CUST047 | D72: Gerald Murphy | E72: P005 | F72: Blender | G72: Appliances | H72: 3 | I72: 59.99 | J72: Credit Card | K72: West | L72: Basic | M72: 45130 | N72: 179.97 | O72: =IF(A72<>"", IF(O72="", NOW(), O72), "") -> 0 | P72: =COUNTIF($F:$F,F72) -> 29 | Q72: =LEFT(D72,1) & MID(D72,FIND(" ",D72)+1,1) -> GM
A73: TRX0216 | B73: 45490 | C73: CUST041 | D73: Peter Richardson | E73: P008 | F73: Bookshelf | G73: Furniture | H73: 3 | I73: 149.99 | J73: Cash | K73: Central | L73: Premium | M73: 45199 | N73: 449.97 | O73: =IF(A73<>"", IF(O73="", NOW(), O73), "") -> 0 | P73: =COUNTIF($F:$F,F73) -> 35 | Q73: =LEFT(D73,1) & MID(D73,FIND(" ",D73)+1,1) -> PR | V73: Find most frequently purchased product or repeating names using formulas
A74: TRX0131 | B74: 45491 | C74: CUST026 | D74: Karen Hill | E74: P006 | F74: Office Chair | G74: Furniture | H74: 3 | I74: 199.99 | J74: Cash | K74: North | L74: Premium | M74: 45254 | N74: 599.97 | O74: =IF(A74<>"", IF(O74="", NOW(), O74), "") -> 0 | P74: =COUNTIF($F:$F,F74) -> 15 | Q74: =LEFT(D74,1) & MID(D74,FIND(" ",D74)+1,1) -> KH | V74: Frequently | W74: Product
A75: TRX0162 | B75: 45496 | C75: CUST040 | D75: Sharon Butler | E75: P001 | F75: Laptop | G75: Electronics | H75: 1 | I75: 899.99 | J75: Cash | K75: Central | L75: Standard | M75: 45179 | N75: 899.99 | O75: =IF(A75<>"", IF(O75="", NOW(), O75), "") -> 0 | P75: =COUNTIF($F:$F,F75) -> 24 | Q75: =LEFT(D75,1) & MID(D75,FIND(" ",D75)+1,1) -> SB | V75: 35 | W75: =INDEX(F2:F251,MATCH(V75,P2:P251,0),1) -> Bookshelf
A76: TRX0244 | B76: 45497 | C76: CUST013 | D76: Joseph Jackson | E76: P001 | F76: Laptop | G76: Electronics | H76: 5 | I76: 899.99 | J76: Debit Card | K76: South | L76: Standard | M76: 44899 | N76: 4499.95 | O76: =IF(A76<>"", IF(O76="", NOW(), O76), "") -> 0 | P76: =COUNTIF($F:$F,F76) -> 24 | Q76: =LEFT(D76,1) & MID(D76,FIND(" ",D76)+1,1) -> JJ | V76: 34 | W76: =INDEX(F3:F252,MATCH(V76,P3:P252,0),1) -> Keyboard
A77: TRX0006 | B77: 45498 | C77: CUST007 | D77: David Martinez | E77: P005 | F77: Blender | G77: Appliances | H77: 2 | I77: 59.99 | J77: Cash | K77: North | L77: Standard | M77: 45152 | N77: 119.98 | O77: =IF(A77<>"", IF(O77="", NOW(), O77), "") -> 0 | P77: =COUNTIF($F:$F,F77) -> 29 | Q77: =LEFT(D77,1) & MID(D77,FIND(" ",D77)+1,1) -> DM | V77: 31 | W77: =INDEX(F4:F253,MATCH(V77,P4:P253,0),1) -> Smartphone
A78: TRX0215 | B78: 45498 | C78: CUST047 | D78: Gerald Murphy | E78: P009 | F78: Monitor | G78: Electronics | H78: 4 | I78: 249.99 | J78: Debit Card | K78: Central | L78: Standard | M78: 45127 | N78: 999.96 | O78: =IF(A78<>"", IF(O78="", NOW(), O78), "") -> 0 | P78: =COUNTIF($F:$F,F78) -> 26 | Q78: =LEFT(D78,1) & MID(D78,FIND(" ",D78)+1,1) -> GM | V78: 29 | W78: =INDEX(F5:F254,MATCH(V78,P5:P254,0),1) -> Blender
A79: TRX0080 | B79: 45500 | C79: CUST018 | D79: Barbara Young | E79: P009 | F79: Monitor | G79: Electronics | H79: 2 | I79: 249.99 | J79: Cash | K79: North | L79: Premium | M79: 45164 | N79: 499.98 | O79: =IF(A79<>"", IF(O79="", NOW(), O79), "") -> 0 | P79: =COUNTIF($F:$F,F79) -> 26 | Q79: =LEFT(D79,1) & MID(D79,FIND(" ",D79)+1,1) -> BY | V79: 26 | W79: =INDEX(F6:F255,MATCH(V79,P6:P255,0),1) -> Monitor
A80: TRX0228 | B80: 45500 | C80: CUST019 | D80: Daniel King | E80: P007 | F80: Desk | G80: Furniture | H80: 1 | I80: 299.99 | J80: Cash | K80: South | L80: Basic | M80: 44982 | N80: 299.99 | O80: =IF(A80<>"", IF(O80="", NOW(), O80), "") -> 0 | P80: =COUNTIF($F:$F,F80) -> 26 | Q80: =LEFT(D80,1) & MID(D80,FIND(" ",D80)+1,1) -> DK | V80: 24 | W80: =INDEX(F7:F256,MATCH(V80,P7:P256,0),1) -> Laptop
A81: TRX0157 | B81: 45501 | C81: CUST025 | D81: Mark Carter | E81: P010 | F81: Keyboard | G81: Electronics | H81: 2 | I81: 89.99 | J81: PayPal | K81: South | L81: Basic | M81: 44976 | N81: 179.98 | O81: =IF(A81<>"", IF(O81="", NOW(), O81), "") -> 0 | P81: =COUNTIF($F:$F,F81) -> 34 | Q81: =LEFT(D81,1) & MID(D81,FIND(" ",D81)+1,1) -> MC | V81: 16 | W81: =INDEX(F8:F257,MATCH(V81,P8:P257,0),1) -> Headphones
A82: TRX0002 | B82: 45501 | C82: CUST019 | D82: Daniel King | E82: P007 | F82: Desk | G82: Furniture | H82: 3 | I82: 299.99 | J82: Cash | K82: Central | L82: Basic | M82: 44732 | N82: 899.97 | O82: =IF(A82<>"", IF(O82="", NOW(), O82), "") -> 0 | P82: =COUNTIF($F:$F,F82) -> 26 | Q82: =LEFT(D82,1) & MID(D82,FIND(" ",D82)+1,1) -> DK | V82: 15 | W82: =INDEX(F9:F258,MATCH(V82,P9:P258,0),1) -> Office Chair
A83: TRX0217 | B83: 45503 | C83: CUST025 | D83: Mark Carter | E83: P002 | F83: Smartphone | G83: Electronics | H83: 2 | I83: 699.99 | J83: Credit Card | K83: North | L83: Premium | M83: 44999 | N83: 1399.98 | O83: =IF(A83<>"", IF(O83="", NOW(), O83), "") -> 0 | P83: =COUNTIF($F:$F,F83) -> 31 | Q83: =LEFT(D83,1) & MID(D83,FIND(" ",D83)+1,1) -> MC | V83: 14 | W83: =INDEX(F10:F259,MATCH(V83,P10:P259,0),1) -> Coffee Maker
A84: TRX0249 | B84: 45504 | C84: CUST030 | D84: Helen Roberts | E84: P001 | F84: Laptop | G84: Electronics | H84: 4 | I84: 899.99 | J84: Debit Card | K84: South | L84: Standard | M84: 44523 | N84: 3599.96 | O84: =IF(A84<>"", IF(O84="", NOW(), O84), "") -> 0 | P84: =COUNTIF($F:$F,F84) -> 24 | Q84: =LEFT(D84,1) & MID(D84,FIND(" ",D84)+1,1) -> HR
A85: TRX0065 | B85: 45509 | C85: CUST016 | D85: Elizabeth Hall | E85: P008 | F85: Bookshelf | G85: Furniture | H85: 2 | I85: 149.99 | J85: Credit Card | K85: West | L85: Basic | M85: 44542 | N85: 299.98 | O85: =IF(A85<>"", IF(O85="", NOW(), O85), "") -> 0 | P85: =COUNTIF($F:$F,F85) -> 35 | Q85: =LEFT(D85,1) & MID(D85,FIND(" ",D85)+1,1) -> EH
A86: TRX0176 | B86: 45510 | C86: CUST044 | D86: Cynthia Price | E86: P008 | F86: Bookshelf | G86: Furniture | H86: 2 | I86: 149.99 | J86: Debit Card | K86: East | L86: Standard | M86: 44667 | N86: 299.98 | O86: =IF(A86<>"", IF(O86="", NOW(), O86), "") -> 0 | P86: =COUNTIF($F:$F,F86) -> 35 | Q86: =LEFT(D86,1) & MID(D86,FIND(" ",D86)+1,1) -> CP
A87: TRX0101 | B87: 45513 | C87: CUST010 | D87: Maria Garcia | E87: P010 | F87: Keyboard | G87: Electronics | H87: 1 | I87: 89.99 | J87: Credit Card | K87: North | L87: Standard | M87: 45393 | N87: 89.99 | O87: =IF(A87<>"", IF(O87="", NOW(), O87), "") -> 0 | P87: =COUNTIF($F:$F,F87) -> 34 | Q87: =LEFT(D87,1) & MID(D87,FIND(" ",D87)+1,1) -> MG | V87: Compare two lists and extract matching names in a new column
A88: TRX0205 | B88: 45515 | C88: CUST025 | D88: Mark Carter | E88: P007 | F88: Desk | G88: Furniture | H88: 5 | I88: 299.99 | J88: Credit Card | K88: North | L88: Basic | M88: 44965 | N88: 1499.95 | O88: =IF(A88<>"", IF(O88="", NOW(), O88), "") -> 0 | P88: =COUNTIF($F:$F,F88) -> 26 | Q88: =LEFT(D88,1) & MID(D88,FIND(" ",D88)+1,1) -> MC | V88: List1 | W88: List2 | X88: Check_Match
A89: TRX0020 | B89: 45517 | C89: CUST007 | D89: David Martinez | E89: P003 | F89: Headphones | G89: Electronics | H89: 4 | I89: 149.99 | J89: Debit Card | K89: South | L89: Premium | M89: 44820 | N89: 599.96 | O89: =IF(A89<>"", IF(O89="", NOW(), O89), "") -> 0 | P89: =COUNTIF($F:$F,F89) -> 16 | Q89: =LEFT(D89,1) & MID(D89,FIND(" ",D89)+1,1) -> DM | V89: Alice | W89: Bob | X89: =IF(ISNUMBER(MATCH(V89,$W$89:$W$98,0)),"Match","Not Match") -> Not Match
A90: TRX0075 | B90: 45517 | C90: CUST020 | D90: Margaret Wright | E90: P009 | F90: Monitor | G90: Electronics | H90: 5 | I90: 249.99 | J90: PayPal | K90: East | L90: Premium | M90: 44782 | N90: 1249.95 | O90: =IF(A90<>"", IF(O90="", NOW(), O90), "") -> 0 | P90: =COUNTIF($F:$F,F90) -> 26 | Q90: =LEFT(D90,1) & MID(D90,FIND(" ",D90)+1,1) -> MW | V90: Bob | W90: David | X90: =IF(ISNUMBER(MATCH(V90,$W$89:$W$98,0)),"Match","Not Match") -> Match
A91: TRX0098 | B91: 45517 | C91: CUST026 | D91: Karen Hill | E91: P009 | F91: Monitor | G91: Electronics | H91: 3 | I91: 249.99 | J91: PayPal | K91: North | L91: Premium | M91: 44465 | N91: 749.97 | O91: =IF(A91<>"", IF(O91="", NOW(), O91), "") -> 0 | P91: =COUNTIF($F:$F,F91) -> 26 | Q91: =LEFT(D91,1) & MID(D91,FIND(" ",D91)+1,1) -> KH | V91: Charlie | W91: Emma | X91: =IF(ISNUMBER(MATCH(V91,$W$89:$W$98,0)),"Match","Not Match") -> Not Match
A92: TRX0247 | B92: 45517 | C92: CUST046 | D92: Kathleen Bennett | E92: P006 | F92: Office Chair | G92: Furniture | H92: 4 | I92: 199.99 | J92: Cash | K92: North | L92: Standard | M92: 44458 | N92: 799.96 | O92: =IF(A92<>"", IF(O92="", NOW(), O92), "") -> 0 | P92: =COUNTIF($F:$F,F92) -> 15 | Q92: =LEFT(D92,1) & MID(D92,FIND(" ",D92)+1,1) -> KB | V92: David | W92: Kevin | X92: =IF(ISNUMBER(MATCH(V92,$W$89:$W$98,0)),"Match","Not Match") -> Match
A93: TRX0027 | B93: 45519 | C93: CUST028 | D93: Betty Campbell | E93: P006 | F93: Office Chair | G93: Furniture | H93: 5 | I93: 199.99 | J93: Cash | K93: North | L93: Premium | M93: 44991 | N93: 999.95 | O93: =IF(A93<>"", IF(O93="", NOW(), O93), "") -> 0 | P93: =COUNTIF($F:$F,F93) -> 15 | Q93: =LEFT(D93,1) & MID(D93,FIND(" ",D93)+1,1) -> BC | V93: Emma | W93: Liam | X93: =IF(ISNUMBER(MATCH(V93,$W$89:$W$98,0)),"Match","Not Match") -> Match
A94: TRX0140 | B94: 45522 | C94: CUST025 | D94: Mark Carter | E94: P010 | F94: Keyboard | G94: Electronics | H94: 2 | I94: 89.99 | J94: Cash | K94: East | L94: Premium | M94: 44972 | N94: 179.98 | O94: =IF(A94<>"", IF(O94="", NOW(), O94), "") -> 0 | P94: =COUNTIF($F:$F,F94) -> 34 | Q94: =LEFT(D94,1) & MID(D94,FIND(" ",D94)+1,1) -> MC | V94: Frank | W94: Grace | X94: =IF(ISNUMBER(MATCH(V94,$W$89:$W$98,0)),"Match","Not Match") -> Not Match
A95: TRX0132 | B95: 45523 | C95: CUST047 | D95: Gerald Murphy | E95: P001 | F95: Laptop | G95: Electronics | H95: 5 | I95: 899.99 | J95: Debit Card | K95: East | L95: Basic | M95: 44526 | N95: 4499.95 | O95: =IF(A95<>"", IF(O95="", NOW(), O95), "") -> 0 | P95: =COUNTIF($F:$F,F95) -> 24 | Q95: =LEFT(D95,1) & MID(D95,FIND(" ",D95)+1,1) -> GM | V95: Grace | W95: Noah | X95: =IF(ISNUMBER(MATCH(V95,$W$89:$W$98,0)),"Match","Not Match") -> Match
A96: TRX0031 | B96: 45523 | C96: CUST036 | D96: Nancy Collins | E96: P003 | F96: Headphones | G96: Electronics | H96: 3 | I96: 149.99 | J96: PayPal | K96: East | L96: Basic | M96: 44574 | N96: 449.97 | O96: =IF(A96<>"", IF(O96="", NOW(), O96), "") -> 0 | P96: =COUNTIF($F:$F,F96) -> 16 | Q96: =LEFT(D96,1) & MID(D96,FIND(" ",D96)+1,1) -> NC | V96: Hannah | W96: Ishaan | X96: =IF(ISNUMBER(MATCH(V96,$W$89:$W$98,0)),"Match","Not Match") -> Not Match
A97: TRX0236 | B97: 45526 | C97: CUST044 | D97: Cynthia Price | E97: P008 | F97: Bookshelf | G97: Furniture | H97: 5 | I97: 149.99 | J97: Credit Card | K97: Central | L97: Basic | M97: 45310 | N97: 749.95 | O97: =IF(A97<>"", IF(O97="", NOW(), O97), "") -> 0 | P97: =COUNTIF($F:$F,F97) -> 35 | Q97: =LEFT(D97,1) & MID(D97,FIND(" ",D97)+1,1) -> CP | V97: Ishaan | W97: Olivia | X97: =IF(ISNUMBER(MATCH(V97,$W$89:$W$98,0)),"Match","Not Match") -> Match
A98: TRX0001 | B98: 45528 | C98: CUST039 | D98: Lawrence Reed | E98: P004 | F98: Coffee Maker | G98: Appliances | H98: 3 | I98: 79.99 | J98: Cash | K98: Central | L98: Premium | M98: 44779 | N98: 239.97 | O98: =IF(A98<>"", IF(O98="", NOW(), O98), "") -> 0 | P98: =COUNTIF($F:$F,F98) -> 14 | Q98: =LEFT(D98,1) & MID(D98,FIND(" ",D98)+1,1) -> LR | V98: Jack | W98: Paul | X98: =IF(ISNUMBER(MATCH(V98,$W$89:$W$98,0)),"Match","Not Match") -> Not Match
A99: TRX0037 | B99: 45528 | C99: CUST035 | D99: Harry Morgan | E99: P009 | F99: Monitor | G99: Electronics | H99: 2 | I99: 249.99 | J99: Cash | K99: South | L99: Standard | M99: 44572 | N99: 499.98 | O99: =IF(A99<>"", IF(O99="", NOW(), O99), "") -> 0 | P99: =COUNTIF($F:$F,F99) -> 26 | Q99: =LEFT(D99,1) & MID(D99,FIND(" ",D99)+1,1) -> HM
A100: TRX0058 | B100: 45532 | C100: CUST047 | D100: Gerald Murphy | E100: P002 | F100: Smartphone | G100: Electronics | H100: 1 | I100: 699.99 | J100: Cash | K100: Central | L100: Premium | M100: 44497 | N100: 699.99 | O100: =IF(A100<>"", IF(O100="", NOW(), O100), "") -> 0 | P100: =COUNTIF($F:$F,F100) -> 31 | Q100: =LEFT(D100,1) & MID(D100,FIND(" ",D100)+1,1) -> GM
A101: TRX0170 | B101: 45532 | C101: CUST034 | D101: Carol Evans | E101: P003 | F101: Headphones | G101: Electronics | H101: 3 | I101: 149.99 | J101: Cash | K101: West | L101: Premium | M101: 45212 | N101: 449.97 | O101: =IF(A101<>"", IF(O101="", NOW(), O101), "") -> 0 | P101: =COUNTIF($F:$F,F101) -> 16 | Q101: =LEFT(D101,1) & MID(D101,FIND(" ",D101)+1,1) -> CE
A102: TRX0248 | B102: 45534 | C102: CUST032 | D102: Sandra Phillips | E102: P002 | F102: Smartphone | G102: Electronics | H102: 2 | I102: 699.99 | J102: Credit Card | K102: North | L102: Premium | M102: 44421 | N102: 1399.98 | O102: =IF(A102<>"", IF(O102="", NOW(), O102), "") -> 0 | P102: =COUNTIF($F:$F,F102) -> 31 | Q102: =LEFT(D102,1) & MID(D102,FIND(" ",D102)+1,1) -> SP
A103: TRX0099 | B103: 45537 | C103: CUST034 | D103: Carol Evans | E103: P009 | F103: Monitor | G103: Electronics | H103: 1 | I103: 249.99 | J103: Credit Card | K103: West | L103: Premium | M103: 44685 | N103: 249.99 | O103: =IF(A103<>"", IF(O103="", NOW(), O103), "") -> 0 | P103: =COUNTIF($F:$F,F103) -> 26 | Q103: =LEFT(D103,1) & MID(D103,FIND(" ",D103)+1,1) -> CE
A104: TRX0074 | B104: 45537 | C104: CUST023 | D104: Paul Baker | E104: P009 | F104: Monitor | G104: Electronics | H104: 1 | I104: 249.99 | J104: Debit Card | K104: North | L104: Premium | M104: 45332 | N104: 249.99 | O104: =IF(A104<>"", IF(O104="", NOW(), O104), "") -> 0 | P104: =COUNTIF($F:$F,F104) -> 26 | Q104: =LEFT(D104,1) & MID(D104,FIND(" ",D104)+1,1) -> PB
A105: TRX0225 | B105: 45538 | C105: CUST039 | D105: Lawrence Reed | E105: P002 | F105: Smartphone | G105: Electronics | H105: 2 | I105: 699.99 | J105: Debit Card | K105: Central | L105: Premium | M105: 44870 | N105: 1399.98 | O105: =IF(A105<>"", IF(O105="", NOW(), O105), "") -> 0 | P105: =COUNTIF($F:$F,F105) -> 31 | Q105: =LEFT(D105,1) & MID(D105,FIND(" ",D105)+1,1) -> LR
A106: TRX0100 | B106: 45541 | C106: CUST031 | D106: Steven Turner | E106: P005 | F106: Blender | G106: Appliances | H106: 3 | I106: 59.99 | J106: Credit Card | K106: Central | L106: Premium | M106: 44717 | N106: 179.97 | O106: =IF(A106<>"", IF(O106="", NOW(), O106), "") -> 0 | P106: =COUNTIF($F:$F,F106) -> 29 | Q106: =LEFT(D106,1) & MID(D106,FIND(" ",D106)+1,1) -> ST
A107: TRX0142 | B107: 45544 | C107: CUST002 | D107: Emma Wilson | E107: P005 | F107: Blender | G107: Appliances | H107: 3 | I107: 59.99 | J107: PayPal | K107: East | L107: Standard | M107: 44748 | N107: 179.97 | O107: =IF(A107<>"", IF(O107="", NOW(), O107), "") -> 0 | P107: =COUNTIF($F:$F,F107) -> 29 | Q107: =LEFT(D107,1) & MID(D107,FIND(" ",D107)+1,1) -> EW
A108: TRX0112 | B108: 45544 | C108: CUST008 | D108: Jennifer Taylor | E108: P004 | F108: Coffee Maker | G108: Appliances | H108: 4 | I108: 79.99 | J108: Cash | K108: North | L108: Basic | M108: 44530 | N108: 319.96 | O108: =IF(A108<>"", IF(O108="", NOW(), O108), "") -> 0 | P108: =COUNTIF($F:$F,F108) -> 14 | Q108: =LEFT(D108,1) & MID(D108,FIND(" ",D108)+1,1) -> JT
A109: TRX0161 | B109: 45545 | C109: CUST017 | D109: Charles Allen | E109: P004 | F109: Coffee Maker | G109: Appliances | H109: 1 | I109: 79.99 | J109: Cash | K109: West | L109: Basic | M109: 44693 | N109: 79.99 | O109: =IF(A109<>"", IF(O109="", NOW(), O109), "") -> 0 | P109: =COUNTIF($F:$F,F109) -> 14 | Q109: =LEFT(D109,1) & MID(D109,FIND(" ",D109)+1,1) -> CA
A110: TRX0108 | B110: 45547 | C110: CUST024 | D110: Dorothy Nelson | E110: P007 | F110: Desk | G110: Furniture | H110: 3 | I110: 299.99 | J110: Credit Card | K110: Central | L110: Premium | M110: 44494 | N110: 899.97 | O110: =IF(A110<>"", IF(O110="", NOW(), O110), "") -> 0 | P110: =COUNTIF($F:$F,F110) -> 26 | Q110: =LEFT(D110,1) & MID(D110,FIND(" ",D110)+1,1) -> DN
... A251: TRX0064 | B251: 45758 | C251: CUST031 | D251: Steven Turner | E251: P010 | F251: Keyboard | G251: Electronics | H251: 3 | I251: 89.99 | J251: Debit Card | K251: North | L251: Premium | M251: 44878 | N251: 269.97 | O251: =IF(A251<>"", IF(O251="", NOW(), O251), "") -> 0 | P251: =COUNTIF($F:$F,F251) -> 34 | Q251: =LEFT(D251,1) & MID(D251,FIND(" ",D251)+1,1) -> ST
O252: =IF(A252<>"", IF(P252="", NOW(), P252), "")

Sheet  Top 5 Customer
A1: Customer_Name | B1: Total_Revenue_per_Customer | C1: High value Customer
A2: Paul Baker | B2: =SUMIFS('Final Project Dataset'!N2:N251,'Final Project Dataset'!D2:D251,' Top 5 Customer'!A2) -> 8309.74 | C2: =IF(B2>7000,"High Value","Normal") -> High Value | E2: Rank | F2: Largest Revenue | G2: Customer_Name
A3: Joseph Jackson | B3: =SUMIFS('Final Project Dataset'!N3:N252,'Final Project Dataset'!D3:D252,' Top 5 Customer'!A3) -> 6949.84 | C3: =IF(B3>7000,"High Value","Normal") -> Normal | E3: 1 | F3: =LARGE(B2:B52,1) -> 15659.65 | G3: =INDEX(A2:A52,MATCH(F3,B2:B52,0),1) -> Mark Carter
A4: Kevin Scott | B4: =SUMIFS('Final Project Dataset'!N4:N253,'Final Project Dataset'!D4:D253,' Top 5 Customer'!A4) -> 3259.87 | C4: =IF(B4>7000,"High Value","Normal") -> Normal | E4: 2 | F4: =LARGE(B3:B53,2) -> 11919.77 | G4: =INDEX(A3:A53,MATCH(F4,B3:B53,0),1) -> Edward Mitchell
A5: Kathleen Bennett | B5: =SUMIFS('Final Project Dataset'!N5:N254,'Final Project Dataset'!D5:D254,' Top 5 Customer'!A5) -> 4309.81 | C5: =IF(B5>7000,"High Value","Normal") -> Normal | E5: 3 | F5: =LARGE(B4:B54,3) -> 10649.8 | G5: =INDEX(A4:A54,MATCH(F5,B4:B54,0),1) -> Barbara Young
A6: Michael Brown | B6: =SUMIFS('Final Project Dataset'!N6:N255,'Final Project Dataset'!D6:D255,' Top 5 Customer'!A6) -> 6169.74 | C6: =IF(B6>7000,"High Value","Normal") -> Normal | E6: 4 | F6: =LARGE(B5:B55,4) -> 9799.73 | G6: =INDEX(A5:A55,MATCH(F6,B5:B55,0),1) -> Patricia Moore
A7: Dorothy Nelson | B7: =SUMIFS('Final Project Dataset'!N7:N256,'Final Project Dataset'!D7:D256,' Top 5 Customer'!A7) -> 8269.79 | C7: =IF(B7>7000,"High Value","Normal") -> High Value | E7: 5 | F7: =LARGE(B6:B56,5) -> 8269.79 | G7: =INDEX(A6:A56,MATCH(F7,B6:B56,0),1) -> Dorothy Nelson
A8: Charles Allen | B8: =SUMIFS('Final Project Dataset'!N8:N257,'Final Project Dataset'!D8:D257,' Top 5 Customer'!A8) -> 5089.73 | C8: =IF(B8>7000,"High Value","Normal") -> Normal
A9: Robert Thomas | B9: =SUMIFS('Final Project Dataset'!N9:N258,'Final Project Dataset'!D9:D258,' Top 5 Customer'!A9) -> 3509.9 | C9: =IF(B9>7000,"High Value","Normal") -> Normal
A10: Karen Hill | B10: =SUMIFS('Final Project Dataset'!N10:N259,'Final Project Dataset'!D10:D259,' Top 5 Customer'!A10) -> 8009.77 | C10: =IF(B10>7000,"High Value","Normal") -> High Value
A11: Susan Green | B11: =SUMIFS('Final Project Dataset'!N11:N260,'Final Project Dataset'!D11:D260,' Top 5 Customer'!A11) -> 1979.89 | C11: =IF(B11>7000,"High Value","Normal") -> Normal
A12: Peter Richardson | B12: =SUMIFS('Final Project Dataset'!N12:N261,'Final Project Dataset'!D12:D261,' Top 5 Customer'!A12) -> 5949.85 | C12: =IF(B12>7000,"High Value","Normal") -> Normal
A13: Dennis Gray | B13: =SUMIFS('Final Project Dataset'!N13:N262,'Final Project Dataset'!D13:D262,' Top 5 Customer'!A13) -> 479.92 | C13: =IF(B13>7000,"High Value","Normal") -> Normal
A14: Michelle Rogers | B14: =SUMIFS('Final Project Dataset'!N14:N263,'Final Project Dataset'!D14:D263,' Top 5 Customer'!A14) -> 4199.94 | C14: =IF(B14>7000,"High Value","Normal") -> Normal
A15: George Adams | B15: =SUMIFS('Final Project Dataset'!N15:N264,'Final Project Dataset'!D15:D264,' Top 5 Customer'!A15) -> 3779.93 | C15: =IF(B15>7000,"High Value","Normal") -> Normal
A16: Mark Carter | B16: =SUMIFS('Final Project Dataset'!N16:N265,'Final Project Dataset'!D16:D265,' Top 5 Customer'!A16) -> 15659.65 | C16: =IF(B16>7000,"High Value","Normal") -> High Value
A17: Maria Garcia | B17: =SUMIFS('Final Project Dataset'!N17:N266,'Final Project Dataset'!D17:D266,' Top 5 Customer'!A17) -> 1909.93 | C17: =IF(B17>7000,"High Value","Normal") -> Normal
A18: Virginia Sanders | B18: =SUMIFS('Final Project Dataset'!N18:N267,'Final Project Dataset'!D18:D267,' Top 5 Customer'!A18) -> 4789.79 | C18: =IF(B18>7000,"High Value","Normal") -> Normal
A19: Barbara Young | B19: =SUMIFS('Final Project Dataset'!N19:N268,'Final Project Dataset'!D19:D268,' Top 5 Customer'!A19) -> 10649.8 | C19: =IF(B19>7000,"High Value","Normal") -> High Value
... A52: John Smith | B52: =SUMIFS('Final Project Dataset'!N52:N301,'Final Project Dataset'!D52:D301,' Top 5 Customer'!A52) -> 599.96 | C52: =IF(B52>7000,"High Value","Normal") -> Normal
